halal_image_downloader/__init__.py
halal_image_downloader/cli.py
halal_image_downloader/extractors/__init__.py
halal_image_downloader/extractors/base_extractor.py
halal_image_downloader/extractors/instagram/__init__.py
halal_image_downloader/extractors/instagram/direct/__init__.py
halal_image_downloader/extractors/instagram/direct/core.py
halal_image_downloader/extractors/instagram/direct/media.py
halal_image_downloader/extractors/instagram/direct/navigate_download.py
halal_image_downloader/extractors/instagram/direct/overlays.py
halal_image_downloader/extractors/instagram/direct/selectors.py
halal_image_downloader/extractors/instagram/saveclip/__init__.py
halal_image_downloader/extractors/instagram/saveclip/analysis.py
halal_image_downloader/extractors/instagram/saveclip/core.py
halal_image_downloader/extractors/instagram/saveclip/navigation.py
halal_image_downloader/extractors/legacy/instagram.py
halal_image_downloader/extractors/legacy/instagram_direct.py
halal_image_downloader/extractors/legacy/pinterest.py
halal_image_downloader/extractors/legacy/reddit.py
halal_image_downloader/extractors/legacy/twitter.py
halal_image_downloader/extractors/pinterest/__init__.py
halal_image_downloader/extractors/pinterest/core.py
halal_image_downloader/extractors/pinterest/images.py
halal_image_downloader/extractors/pinterest/parse.py
halal_image_downloader/extractors/reddit/__init__.py
halal_image_downloader/extractors/reddit/core.py
halal_image_downloader/extractors/reddit/images.py
halal_image_downloader/extractors/reddit/parse.py
halal_image_downloader/extractors/twitter/__init__.py
halal_image_downloader/extractors/twitter/core.py
halal_image_downloader/extractors/twitter/images.py
halal_image_downloader/extractors/twitter/parse.py
halal_image_downloader/utils/browser.py
halal_image_downloader-2025.10.13.dist-info/WHEEL
halal_image_downloader-2025.10.13.dist-info/entry_points.txt
halal_image_downloader-2025.10.13.dist-info/METADATA
halal_image_downloader-2025.10.13.dist-info/RECORD
