Metadata-Version: 2.3
Name: halal-image-downloader
Version: 2025.10.13
Summary: A command-line tool for fast and reliable image downloading from supported sources.
Keywords: image,downloader,social-media,instagram,pinterest,twitter,cli
Author: Asdmir786
Author-email: Asdmir786 <asmir.alams.com@gmail.com>
Classifier: Development Status :: 4 - Beta
Classifier: Environment :: Console
Classifier: Intended Audience :: End Users/Desktop
Classifier: License :: OSI Approved :: MIT License
Classifier: Operating System :: OS Independent
Classifier: Programming Language :: Python :: 3
Classifier: Programming Language :: Python :: 3.11
Classifier: Programming Language :: Python :: 3.12
Classifier: Programming Language :: Python :: 3.13
Classifier: Programming Language :: Python :: 3.14
Classifier: Topic :: Internet :: WWW/HTTP
Classifier: Topic :: Multimedia :: Graphics
Classifier: Topic :: Software Development :: Libraries :: Python Modules
Requires-Dist: beautifulsoup4>=4.13.5
Requires-Dist: fake-useragent>=2.2.0
Requires-Dist: httpx[http2]>=0.28.1
Requires-Dist: pillow>=11.3.0
Requires-Dist: playwright>=1.55.0
Requires-Dist: requests>=2.32.5
Requires-Python: >=3.11
Project-URL: Homepage, https://github.com/Asdmir786/halal-image-downloader
Project-URL: Issues, https://github.com/Asdmir786/halal-image-downloader/issues
Project-URL: Repository, https://github.com/Asdmir786/halal-image-downloader
